relic/__init__.py
relic/aug.py
relic/metrics.py
relic/relic.py
relic/stl10_eval.py
relic/utils.py
relic/custom_datasets/__init__.py
relic/custom_datasets/custom_datasets.py
relic/custom_datasets/huggingface_dataset.py
relic/encoders/__init__.py
relic/encoders/models.py
relic_pytorch-0.4.1.dist-info/LICENSE
relic_pytorch-0.4.1.dist-info/METADATA
relic_pytorch-0.4.1.dist-info/WHEEL
relic_pytorch-0.4.1.dist-info/entry_points.txt
relic_pytorch-0.4.1.dist-info/top_level.txt
relic_pytorch-0.4.1.dist-info/RECORD
